README.rst
setup.py
audio_display/__init__.py
audio_display/fft2png.py
audio_display/wavfile.py
audio_display.egg-info/PKG-INFO
audio_display.egg-info/SOURCES.txt
audio_display.egg-info/dependency_links.txt
audio_display.egg-info/entry_points.txt
audio_display.egg-info/requires.txt
audio_display.egg-info/top_level.txt